[{"id":1,"nome":"Mochila","descricao":"Uma mochila \u00e9, em sua forma mais simples, um saco de lona ou tecido sint\u00e9tico resistente que \u00e9 carregado nas costas de uma pessoa, e apoiada atrav\u00e9s de duas al\u00e7as que passam por cima dos ombros. Utilizada por soldados, excursionistas, escolares, etc. para transportar artigos de uso pessoal, provis\u00f5es, material e itens variados. Foi criada originalmente na \u00c1frica antiga, feita de peles de animais.","preco":"120.00","foto":"mochila.jpg"},{"id":2,"nome":"Livro","descricao":"Livro (do latim liber) \u00e9 um objeto transport\u00e1vel, composto por p\u00e1ginas encadernadas, contendo texto manuscrito ou impresso e\/ou imagens e que forma uma publica\u00e7\u00e3o unit\u00e1ria (ou foi concebido como tal) ou a parte principal de um trabalho liter\u00e1rio, cient\u00edfico ou outro, formando um volume.","preco":"50.00","foto":"open-textbook-762687.jpg"}]